edc_sites/__init__.py
edc_sites/admin_site.py
edc_sites/apps.py
edc_sites/auths.py
edc_sites/exceptions.py
edc_sites/form_validator_mixin.py
edc_sites/forms.py
edc_sites/managers.py
edc_sites/modelform_mixins.py
edc_sites/post_migrate_signals.py
edc_sites/site.py
edc_sites/system_checks.py
edc_sites/urls.py
edc_sites/view_mixins.py
edc_sites/admin/__init__.py
edc_sites/admin/list_filters.py
edc_sites/admin/site_admin.py
edc_sites/admin/site_fieldset_tuple.py
edc_sites/admin/site_model_admin_mixin.py
edc_sites/management/__init__.py
edc_sites/management/commands/__init__.py
edc_sites/management/commands/sync_sites.py
edc_sites/migrations/0001_initial.py
edc_sites/migrations/0002_auto_20190922_0452.py
edc_sites/migrations/0003_siteprofile_country.py
edc_sites/migrations/0004_siteprofile_country_code.py
edc_sites/migrations/0005_auto_20210423_1451.py
edc_sites/migrations/0006_siteprofile_languages.py
edc_sites/migrations/0007_edcpermissions.py
edc_sites/migrations/0008_delete_edcsite_remove_siteprofile_description.py
edc_sites/migrations/__init__.py
edc_sites/model_mixins/__init__.py
edc_sites/model_mixins/site_model_mixin.py
edc_sites/models/__init__.py
edc_sites/models/edc_permissions.py
edc_sites/models/site_profile.py
edc_sites/single_site/__init__.py
edc_sites/single_site/get_languages.py
edc_sites/single_site/get_languages_from_settings.py
edc_sites/single_site/single_site.py
edc_sites/templatetags/__init__.py
edc_sites/templatetags/edc_sites_extras.py
edc_sites/tests/__init__.py
edc_sites/tests/admin.py
edc_sites/tests/models.py
edc_sites/tests/site_test_case_mixin.py
edc_sites/tests/sites.py
edc_sites/tests/test_settings.py
edc_sites/tests/urls.py
edc_sites/tests/etc/user-aes-local.key
edc_sites/tests/etc/user-aes-restricted.key
edc_sites/tests/etc/user-rsa-local-private.pem
edc_sites/tests/etc/user-rsa-local-public.pem
edc_sites/tests/etc/user-rsa-restricted-private.pem
edc_sites/tests/etc/user-rsa-restricted-public.pem
edc_sites/tests/etc/user-salt-local.key
edc_sites-1.1.0.dist-info/licenses/AUTHORS
edc_sites-1.1.0.dist-info/licenses/LICENSE
edc_sites-1.1.0.dist-info/METADATA
edc_sites-1.1.0.dist-info/WHEEL
edc_sites-1.1.0.dist-info/top_level.txt
edc_sites-1.1.0.dist-info/RECORD
